django_pivot/__init__.py
django_pivot/histogram.py
django_pivot/pivot.py
django_pivot/utils.py
django_pivot/tests/__init__.py
django_pivot/tests/test_mysql_settings.py
django_pivot/tests/test_postgres_settings.py
django_pivot/tests/test_sqlite_settings.py
django_pivot/tests/pivot/__init__.py
django_pivot/tests/pivot/models.py
django_pivot/tests/pivot/test.py
django_pivot-1.9.0.dist-info/LICENSE
django_pivot-1.9.0.dist-info/METADATA
django_pivot-1.9.0.dist-info/WHEEL
django_pivot-1.9.0.dist-info/top_level.txt
django_pivot-1.9.0.dist-info/RECORD
