Metadata-Version: 2.1
Name: django-pivot
Version: 1.9.0
Summary: Create pivot tables and histograms from ORM querysets
Home-page: https://github.com/martsberger/django-pivot
Author: Brad Martsberger
Author-email: bmarts@lumere.com
License: MIT
Download-URL: https://github.com/martsberger/django-pivot/archive/1.9.0.tar.gz
Platform: UNKNOWN
Classifier: Programming Language :: Python :: 3
Classifier: Programming Language :: Python :: 3.6
Classifier: Programming Language :: Python :: 3.7
Classifier: Programming Language :: Python :: 3.8
Requires-Dist: django (>=2.2.0)
